{
  "name": "casamento_soho_auto",
  "references": [
    "D:/2026-04-11 - Casamento - Debora Seimaru e Lucas - Soho/02 AUDIOS"
  ],
  "targets": [
    "D:/2026-04-11 - Casamento - Debora Seimaru e Lucas - Soho/01 CAMERAS"
  ],
  "reference_filter": [
    "DJI_06_20260411_165508",
    "DJI_07_20260411_172612",
    "DJI_15_20260411_170802",
    "DJI_16_20260411_173907",
    "MONO-017"
  ],
  "target_range": [
    "A7IV_20260411_9715..A7IV_20260411_9729",
    "ZVE10_02_20260411_9450..ZVE10_02_20260411_9453",
    "ZVE10_01_20260411_9647..ZVE10_01_20260411_9651",
    "C0020..C0029"
  ],
  "ignore_metadata": true,
  "use_camera_clock_model": true,
  "output": "output/casamento_soho_auto.xml"
}
